dramatiq_header/__init__.py
dramatiq_header-0.1.2.dist-info/LICENSE.yml
dramatiq_header-0.1.2.dist-info/METADATA
dramatiq_header-0.1.2.dist-info/WHEEL
dramatiq_header-0.1.2.dist-info/RECORD
