Metadata-Version: 2.1
Name: dramatiq-header
Version: 0.1.2
Summary: Expose dramatiq headers via an options message through a thread-local variable in middleware.
Home-page: https://github.com/guedesfelipe/dramatiq-header
Keywords: dramatiq,header,dramatiq header,rabbitmq
Author: Felipe Guedes
Author-email: contatofelipeguedes@gmail.com
Requires-Python: >=3.10,<4.0
Classifier: Programming Language :: Python :: 3
Classifier: Programming Language :: Python :: 3.10
Classifier: Programming Language :: Python :: 3.11
Classifier: Programming Language :: Python :: 3.12
Requires-Dist: dramatiq (>=1.15.0,<2.0.0)
Project-URL: Documentation, https://github.com/guedesfelipe/dramatiq-header
Project-URL: Repository, https://github.com/guedesfelipe/dramatiq-header
